AUTHORS.rst
CONTRIBUTING.rst
HISTORY.rst
LICENSE
MANIFEST.in
README.rst
setup.cfg
setup.py
docs/Makefile
docs/authors.rst
docs/conf.py
docs/contributing.rst
docs/history.rst
docs/index.rst
docs/installation.rst
docs/make.bat
docs/modules.rst
docs/readme.rst
docs/ultra_random_uuid.rst
docs/usage.rst
docs/_build/html/_static/ajax-loader.gif
docs/_build/html/_static/comment-bright.png
docs/_build/html/_static/comment-close.png
docs/_build/html/_static/comment.png
docs/_build/html/_static/down-pressed.png
docs/_build/html/_static/down.png
docs/_build/html/_static/file.png
docs/_build/html/_static/minus.png
docs/_build/html/_static/plus.png
docs/_build/html/_static/up-pressed.png
docs/_build/html/_static/up.png
tests/__init__.py
tests/test_ultra_random_uuid.py
ultra_random_uuid/__init__.py
ultra_random_uuid/cli.py
ultra_random_uuid/ultra_random_uuid.py
ultra_random_uuid.egg-info/PKG-INFO
ultra_random_uuid.egg-info/SOURCES.txt
ultra_random_uuid.egg-info/dependency_links.txt
ultra_random_uuid.egg-info/entry_points.txt
ultra_random_uuid.egg-info/not-zip-safe
ultra_random_uuid.egg-info/requires.txt
ultra_random_uuid.egg-info/top_level.txt