Metadata-Version: 1.1
Name: ultra-random-uuid
Version: 0.1.0
Summary: Python Ultra Random UUID
Home-page: https://github.com/saduqz/ultra_random_uuid
Author: Andres Duque Hincapie
Author-email: saduqz@gmail.com
License: MIT license
Keywords: ultra_random_uuid
Platform: UNKNOWN
Classifier: Development Status :: 2 - Pre-Alpha
Classifier: Intended Audience :: Developers
Classifier: License :: OSI Approved :: MIT License
Classifier: Natural Language :: English
Classifier: Programming Language :: Python :: 2
Classifier: Programming Language :: Python :: 2.7
Classifier: Programming Language :: Python :: 3
Classifier: Programming Language :: Python :: 3.4
Classifier: Programming Language :: Python :: 3.5
Classifier: Programming Language :: Python :: 3.6
